fetch_gitignore/__init__.py
fetch_gitignore/core.py
untrack_gitignored_files/__init__.py
untrack_gitignored_files/core.py
untrack_gitignored_files-0.6.0.dist-info/METADATA
untrack_gitignored_files-0.6.0.dist-info/WHEEL
untrack_gitignored_files-0.6.0.dist-info/entry_points.txt
untrack_gitignored_files-0.6.0.dist-info/top_level.txt
untrack_gitignored_files-0.6.0.dist-info/RECORD
